yd_test_python_package_00/__init__.py
yd_test_python_package_00/my_method.py
yd_test_python_package_00-0.0.2.dist-info/LICENSE
yd_test_python_package_00-0.0.2.dist-info/WHEEL
yd_test_python_package_00-0.0.2.dist-info/METADATA
yd_test_python_package_00-0.0.2.dist-info/RECORD
